{
  "listStudent": [
    {
      "Gender": "female",
      "Email": "clkao@att.net",
      "PhoneNumber": "0111111111",
      "Score": 10,
      "ClassId": 1,
      "Id": 1,
      "Name": "Averie Rocha"
    },
    {
      "Gender": "female",
      "Email": "kannan@icloud.com",
      "PhoneNumber": "0222222222",
      "Score": 20,
      "ClassId": 2,
      "Id": 2,
      "Name": "Sasha Gould"
    },
    {
      "Gender": "male",
      "Email": "jbarta@mac.com",
      "PhoneNumber": "0333333333",
      "Score": 30,
      "ClassId": 3,
      "Id": 3,
      "Name": "Azul Kelley"
    },
    {
      "Gender": "male",
      "Email": "willg@live.com",
      "PhoneNumber": "0444444444",
      "Score": 40,
      "ClassId": 2,
      "Id": 4,
      "Name": "Yasmine Page"
    },
    {
      "Gender": "female",
      "Email": "lamprecht@gmail.com",
      "PhoneNumber": "0555555555",
      "Score": 50,
      "ClassId": 3,
      "Id": 5,
      "Name": "Kellen Peterson"
    },
    {
      "Gender": "female",
      "Email": "miyop@comcast.net",
      "PhoneNumber": "0666666666",
      "Score": 60,
      "ClassId": 3,
      "Id": 6,
      "Name": "Gisselle Mejia"
    },
    {
      "Gender": "male",
      "Email": "earmstro@att.net",
      "PhoneNumber": "0777777777",
      "Score": 70,
      "ClassId": 2,
      "Id": 7,
      "Name": "Darius Wells"
    },
    {
      "Gender": "female",
      "Email": "presoff@yahoo.com",
      "PhoneNumber": "0888888888",
      "Score": 80,
      "ClassId": 1,
      "Id": 8,
      "Name": "Lucy Underwood"
    },
    {
      "Gender": "male",
      "Email": "skythe@aol.com",
      "PhoneNumber": "0999999999",
      "Score": 90,
      "ClassId": 1,
      "Id": 9,
      "Name": "Wade Santos"
    },
    {
      "Gender": "female",
      "Email": "pierce@msn.com",
      "PhoneNumber": "0122222222",
      "Score": 5,
      "ClassId": 2,
      "Id": 10,
      "Name": "Deanna Cummings"
    },
    {
      "Gender": "female",
      "Email": "hllam@live.com",
      "PhoneNumber": "0322222222",
      "Score": 15,
      "ClassId": 1,
      "Id": 11,
      "Name": "Carsen Lin"
    },
    {
      "Gender": "male",
      "Email": "mastinfo@hotmail.com",
      "PhoneNumber": "0433333333",
      "Score": 25,
      "ClassId": 1,
      "Id": 12,
      "Name": "Davin Atkinson"
    },
    {
      "Gender": "female",
      "Email": "nichoj@sbcglobal.net",
      "PhoneNumber": "0544444444",
      "Score": 35,
      "ClassId": 3,
      "Id": 13,
      "Name": "Evie Fisher"
    },
    {
      "Gender": "male",
      "Email": "thurston@live.com",
      "PhoneNumber": "0655555555",
      "Score": 45,
      "ClassId": 2,
      "Id": 14,
      "Name": "Ishaan Steele"
    },
    {
      "Gender": "female",
      "Email": "akoblin@optonline.net",
      "PhoneNumber": "0766666666",
      "Score": 55,
      "ClassId": 1,
      "Id": 15,
      "Name": "Iliana Archer"
    },
    {
      "Gender": "male",
      "Email": "raines@verizon.net",
      "PhoneNumber": "0877777777",
      "Score": 65,
      "ClassId": 3,
      "Id": 16,
      "Name": "Kaliyah Logan"
    },
    {
      "Gender": "female",
      "Email": "oracle@mac.com",
      "PhoneNumber": "0877777777",
      "Score": 75,
      "ClassId": 2,
      "Id": 17,
      "Name": "Mylie Barr"
    },
    {
      "Gender": "female",
      "Email": "miyop@comcast.net",
      "PhoneNumber": "0988888888",
      "Score": 85,
      "ClassId": 1,
      "Id": 18,
      "Name": "Pranav Spence"
    },
    {
      "Gender": "male",
      "Email": "duncand@icloud.com",
      "PhoneNumber": "0099999999",
      "Score": 95,
      "ClassId": 3,
      "Id": 19,
      "Name": "Lucy Underwood"
    },
    {
      "Gender": "male",
      "Email": "parsimony@outlook.com",
      "PhoneNumber": "0112222222",
      "Score": 25,
      "ClassId": 1,
      "Id": 20,
      "Name": "Devan Gilbert"
    }
  ]
}